cloudquery_plugin_pb-0.0.50-py3.13-nspkg.pth
cloudquery/discovery_v1/__init__.py
cloudquery/discovery_v1/discovery_pb2.py
cloudquery/discovery_v1/discovery_pb2.pyi
cloudquery/discovery_v1/discovery_pb2_grpc.py
cloudquery/discovery_v1/py.typed
cloudquery/plugin_v3/__init__.py
cloudquery/plugin_v3/arrow.py
cloudquery/plugin_v3/plugin_pb2.py
cloudquery/plugin_v3/plugin_pb2.pyi
cloudquery/plugin_v3/plugin_pb2_grpc.py
cloudquery/plugin_v3/py.typed
cloudquery_plugin_pb-0.0.50.dist-info/licenses/LICENSE
cloudquery_plugin_pb-0.0.50.dist-info/METADATA
cloudquery_plugin_pb-0.0.50.dist-info/WHEEL
cloudquery_plugin_pb-0.0.50.dist-info/namespace_packages.txt
cloudquery_plugin_pb-0.0.50.dist-info/top_level.txt
cloudquery_plugin_pb-0.0.50.dist-info/RECORD
